<annotation>
	<folder>collectedImages</folder>
	<filename>no.ce0cb157-b616-11f0-898c-919b6160ab7e.jpg</filename>
	<path>C:\Users\juili\Downloads\RealTimeObjectDetection-main\Tensorflow\workspace\images\collectedImages\no.ce0cb157-b616-11f0-898c-919b6160ab7e.jpg</path>
	<source>
		<database>Unknown</database>
	</source>
	<size>
		<width>640</width>
		<height>480</height>
		<depth>3</depth>
	</size>
	<segmented>0</segmented>
	<object>
		<name>No</name>
		<pose>Unspecified</pose>
		<truncated>1</truncated>
		<difficult>0</difficult>
		<bndbox>
			<xmin>111</xmin>
			<ymin>362</ymin>
			<xmax>261</xmax>
			<ymax>480</ymax>
		</bndbox>
	</object>
</annotation>
